Main.sv
module Main(
    input [11:0] memoryAddress,
    input [31:0] writeData,
    input readEnable,writeEnable
);

reg[6:0] tagArrayInCache [7:0][3:0]; //5 bits for address + 1 dirty bit(5) + 1 valid bit(6)
// 8 rows for sets 4 columns for ways 
integer dataInCache [7:0] [3:0] [15:0];
// 8 rows for sets 4 columns for ways and 16 for block size, so 16 bytes(integer)
integer Memory[255:0] [15:0];
// 4096 bytes of memory, each block is of size 16 bytes.
integer counter[7:0][3:0];
reg hitmiss;

// reg [11:0] memoryAddress=12'b000000100010;//Memory[2][2]
// Memory[2][2]=14;
// integer writeData;
reg[4:0] tagNumber;
// tagNumber=memoryAddress [11:7];
reg[4:0] hittag;
reg[6:0] temp;
integer set_number;
integer offset,way_number;
integer blockNumberInMemory;
integer missmaxcount;
integer addressToMemory;
integer empty;
integer data;
integer position;
integer readmiss;
integer readhit;
integer writehit;
integer writemiss;
integer way_number_temp;


//setting initial values
initial begin
    readmiss=0;
    readhit=0;
    writehit=0;
    writemiss=0;
    for(integer i=0; i<8; i=i+1) begin
        for(integer j=0; j<4;j++) begin
            tagArrayInCache[i][j]=7'b0;
            counter[i][j]=0;
            for(integer k=0;k<16;k=k+1)begin
                dataInCache[i][j][k]=0;
            end
        end
    end
    for(integer i=0; i<256; i=i+1) begin
        for(integer j=0; j<16;j++) begin
            Memory[i][j] = 0;
        end
    end
end
always @* begin
    

//taking input(incompolete)...............................................................................................................
// reg readEnable=1'b1;
// reg writeEnable=1'b0;
// reg [11:0] memoryAddress=12'b000000100010;//Memory[2][2]
// Memory[2][2]=14;
// integer writeData;
//........................................................................................................................................

//checking hit miss
// reg[4:0] tagNumber;
tagNumber=memoryAddress [11:7];
// reg[4:0] hittag;
set_number=memoryAddress[6]*4+memoryAddress[5]*2+memoryAddress[4];
// integer offset,way_number;
blockNumberInMemory=memoryAddress[11]*128+memoryAddress[10]*64+memoryAddress[9]*32+memoryAddress[8]*16+memoryAddress[7]*8+memoryAddress[6]*4+memoryAddress[5]*2+memoryAddress[4];

hitmiss=1'b0;  
empty=-1;
for(integer i=3;i>=0;i=i-1) begin
  if(tagNumber==tagArrayInCache[set_number][i] [4:0] && tagArrayInCache[set_number][i] [6]==1'b1) begin
    hitmiss=1'b1;
    hittag=tagArrayInCache[set_number][i];//may be redundant
    way_number=i;
    way_number_temp=i;
  end
  if(tagArrayInCache[set_number][i][6]==1'b0) begin
    empty=i;
  end
end
//hit miss complete
for(integer i=0;i<4;i=i+1) begin
    counter[set_number][i]=counter[set_number][i]+1;
end
offset=memoryAddress[3]*8+memoryAddress[2]*4+memoryAddress[1]*2+memoryAddress[0];

if(hitmiss==1'b1) begin//for hit
    if(readEnable==1'b1) begin
        data = dataInCache[set_number][way_number][offset];
        readhit=readhit+1;
        
    end
    if(writeEnable==1'b1) begin
        dataInCache[set_number][way_number][offset]=writeData;
        tagArrayInCache[set_number][way_number] [5]=1'b1;//setting dirty bit to 1
        data = dataInCache[set_number][way_number][offset];
        writehit=writehit+1;
    end
    counter[set_number][way_number]=0;
end

else begin//for miss
    //first we check if any block is empty
    way_number=empty;
    if(empty<0) begin
            //in this case, we will replace a block
            // integer position;
        missmaxcount=-1;
        for(integer i=0;i<=3;i=i+1) begin
            if(missmaxcount<counter[set_number][i])begin
                missmaxcount=counter[set_number][i];
                way_number=i;
            end
        end
        temp=tagArrayInCache[set_number][way_number]; 
        //check if the bit at postion 5 is 1
        if(temp[5]==1'b1) begin //dirty bit is set
            addressToMemory=temp[4]*128+temp[3]*64+temp[2]*32+temp[1]*16+temp[0]*8+set_number; //convert 11-4 bit of previous address(stored in tag) to integer
            for(integer i=0;i<16;i=i+1)begin
                Memory[addressToMemory][i]=dataInCache[set_number][way_number][i];//update in memory
            end
        end
    end
    for(integer i=0;i<16;i=i+1)begin
        dataInCache[set_number][way_number][i]=Memory[blockNumberInMemory][i];
    end
    tagArrayInCache[set_number][way_number][6]=1'b1;//setting validbit
    tagArrayInCache[set_number][way_number][5]=1'b0;//setting dirty bit
    tagArrayInCache[set_number][way_number][4:0]=memoryAddress[11:7];//setting tag in cache                
    if(writeEnable==1'b1)begin//for write
        dataInCache[set_number][way_number][offset]=writeData;
        tagArrayInCache[set_number][way_number][5]=1'b1;//setting dirty bit
        data = dataInCache[set_number][way_number][offset];
        writemiss=writemiss+1;
    end
    if(readEnable==1'b1) begin//for read
        data=dataInCache[set_number][way_number][offset];
        readmiss=readmiss+1;
    end
    for(integer i=0;i<4;i=i+1)begin
        counter[set_number][i]=counter[set_number][i]+1;
    end
    counter[set_number][way_number]=0;
    
        // way_number=postion;        
        
end

end
endmodule

Main_tb.sv
`timescale 1ns / 1ns
`include "Main.sv"

module Main_tb;

// reg hitmiss;
// reg [13:0] tagArrayInCache [7:0] [3:0];
// reg integer set;
// reg [4:0] tag;
// wire [4:0] tagout;
reg [11:0] memoryAddress;
integer writeData;
reg readEnable,writeEnable;

Main uut(memoryAddress,writeData,readEnable,writeEnable);

initial begin
    $dumpfile("Main_tb.vcd");
    $dumpvars(0, Main_tb);
    #20;

    // hitmiss = 1'b1;
    // set = 3'b10;
    // tag = 5'b10001;
    memoryAddress=12'b000000100010;// 2,2 writemiss
    writeData=3;
    readEnable=1'b0;
    writeEnable=1'b1;

    #20;
    memoryAddress=12'b000000100000;//2,0 writehit
    writeData=6;
    readEnable=1'b0;
    writeEnable=1'b1;

    #20;
    memoryAddress=12'b000000100010;// 2,2 readhit
    writeData=3;
    readEnable=1'b1;
    writeEnable=1'b0;

    #20;
    memoryAddress=12'b000001000010;//  4,2 readmiss
    // writeData=3;
    readEnable=1'b1;
    writeEnable=1'b0;

    #20;
    memoryAddress=12'b000010100010;// 10,2 writemiss with way_number 1
    writeData=30;
    readEnable=1'b0;
    writeEnable=1'b1;

    #20;
    memoryAddress=12'b000100100010;// 18,2 readmiss with way_number 2
    // writeData=3;
    readEnable=1'b1;
    writeEnable=1'b0;

    #20;
    memoryAddress=12'b000110100010;// 26,2 readmiss with way_number 3
    // writeData=3;
    readEnable=1'b1;
    writeEnable=1'b0;

    #20;
    memoryAddress=12'b001100100010;// 50,2 readmiss with way_number 0
    // writeData=3;
    readEnable=1'b1;
    writeEnable=1'b0;

    #20;
    memoryAddress=12'b011100100010;// 114,2 writemiss with way_number 1
    writeData=77;
    readEnable=1'b0;
    writeEnable=1'b1;

    #20;

    // hitmiss = 
    // set =
    // tag = 
    /*tagArrayInCache[][] <= 
    tagArrayInCache[][] <= 
    tagArrayInCache[][] <= 
    tagArrayInCache[][] <= 
    tagArrayInCache[][] <= */

end
endmodule

Main_tb.vcd
$date
	Thu Nov 10 04:08:17 2022
$end
$version
	Icarus Verilog
$end
$timescale
	1ns
$end
$scope module Main_tb $end
$var reg 12 ! memoryAddress [11:0] $end
$var reg 1 " readEnable $end
$var reg 1 # writeEnable $end
$var integer 32 $ writeData [31:0] $end
$scope module uut $end
$var wire 12 % memoryAddress [11:0] $end
$var wire 1 " readEnable $end
$var wire 32 & writeData [31:0] $end
$var wire 1 # writeEnable $end
$var reg 1 ' hitmiss $end
$var reg 5 ( hittag [4:0] $end
$var reg 5 ) tagNumber [4:0] $end
$var reg 7 * temp [6:0] $end
$var integer 32 + addressToMemory [31:0] $end
$var integer 32 , blockNumberInMemory [31:0] $end
$var integer 32 - data [31:0] $end
$var integer 32 . empty [31:0] $end
$var integer 32 / missmaxcount [31:0] $end
$var integer 32 0 offset [31:0] $end
$var integer 32 1 readhit [31:0] $end
$var integer 32 2 readmiss [31:0] $end
$var integer 32 3 set_number [31:0] $end
$var integer 32 4 way_number [31:0] $end
$var integer 32 5 way_number_temp [31:0] $end
$var integer 32 6 writehit [31:0] $end
$var integer 32 7 writemiss [31:0] $end
$scope begin $ivl_for_loop0 $end
$var integer 32 8 i [31:0] $end
$scope begin $ivl_for_loop1 $end
$var integer 32 9 j [31:0] $end
$scope begin $ivl_for_loop2 $end
$var integer 32 : k [31:0] $end
$upscope $end
$upscope $end
$upscope $end
$scope begin $ivl_for_loop10 $end
$var integer 32 ; i [31:0] $end
$upscope $end
$scope begin $ivl_for_loop3 $end
$var integer 32 < i [31:0] $end
$scope begin $ivl_for_loop4 $end
$var integer 32 = j [31:0] $end
$upscope $end
$upscope $end
$scope begin $ivl_for_loop5 $end
$var integer 32 > i [31:0] $end
$upscope $end
$scope begin $ivl_for_loop6 $end
$var integer 32 ? i [31:0] $end
$upscope $end
$scope begin $ivl_for_loop7 $end
$var integer 32 @ i [31:0] $end
$upscope $end
$scope begin $ivl_for_loop8 $end
$var integer 32 A i [31:0] $end
$upscope $end
$scope begin $ivl_for_loop9 $end
$var integer 32 B i [31:0] $end
$upscope $end
$upscope $end
$upscope $end
$enddefinitions $end
$comment Show the parameter values. $end
$dumpall
$end
#0
$dumpvars
b10000 B
bx A
b100 @
b100 ?
b11111111111111111111111111111111 >
b10000 =
b100000000 <
b100 ;
b10000 :
b100 9
b1000 8
b0 7
b0 6
bx 5
b11111111111111111111111111111111 4
bx 3
b0 2
b0 1
bx 0
b11111111111111111111111111111111 /
b11111111111111111111111111111111 .
bx -
bx ,
bx +
bx *
bx )
bx (
0'
bx &
bx %
bx $
x#
x"
bx !
$end
#20
b100 ;
b1 7
b11 -
b10000 B
b0 4
b10 0
b100 ?
b0 .
b11111111111111111111111111111111 >
b10 ,
b10 3
b0 )
1#
0"
b11 $
b11 &
b100010 !
b100010 %
#40
b1 6
b110 -
b0 0
b100 ?
b0 5
b0 (
1'
b11111111111111111111111111111111 >
b1 .
b110 $
b110 &
b100000 !
b100000 %
#60
b1 1
b11 -
b10 0
b100 ?
b11111111111111111111111111111111 >
b1 .
1'
0#
1"
b11 $
b11 &
b100010 !
b100010 %
#80
b100 ;
b1 2
b0 -
b10000 B
b100 ?
b11111111111111111111111111111111 >
b0 .
0'
b100 ,
b100 3
b1000010 !
b1000010 %
#100
b100 ;
b10 7
b11110 -
b10000 B
b1 4
b100 ?
b11111111111111111111111111111111 >
b1 .
b1010 ,
b10 3
b1 )
1#
0"
b11110 $
b11110 &
b10100010 !
b10100010 %
#120
b100 ;
b10 2
b0 -
b10000 B
b10 4
b100 ?
b11111111111111111111111111111111 >
b10 .
b10010 ,
b10 )
0#
1"
b100100010 !
b100100010 %
#140
b100 ;
b11 2
b10000 B
b11 4
b100 ?
b11111111111111111111111111111111 >
b11 .
b11010 ,
b11 )
b110100010 !
b110100010 %
#160
b100 ;
b100 2
b10000 B
b10000 A
b10 +
b1100000 *
b111 /
b100 @
b0 4
b100 ?
b11111111111111111111111111111111 >
b11111111111111111111111111111111 .
b110010 ,
b110 )
b1100100010 !
b1100100010 %
#180
b100 ;
b11 7
b1001101 -
b10000 B
b10000 A
b1010 +
b1100001 *
b100 @
b111 /
b1 4
b100 ?
b11111111111111111111111111111111 >
b1110010 ,
b1110 )
1#
0"
b1001101 $
b1001101 &
b11100100010 !
b11100100010 %
